python_ls.pth
python_ls/__init__.py
python_ls/_ls.py
python_ls/_version.py
python_ls-0.1.5.data/data/LICENSE
python_ls-0.1.5.dist-info/METADATA
python_ls-0.1.5.dist-info/RECORD
python_ls-0.1.5.dist-info/WHEEL
python_ls-0.1.5.dist-info/top_level.txt
