Metadata-Version: 2.1
Name: python-ls
Version: 0.1.5
Summary: A better replacement for Python dir() builtin function
Home-page: http://github.com/gabrielcnr/python-ls
Author: Gabriel Reis
Author-email: gabrielcnr@gmail.com
License: MIT
Keywords: python dir ls search attributes
Platform: UNKNOWN
Classifier: Development Status :: 5 - Production/Stable
Classifier: Intended Audience :: Developers
Classifier: License :: OSI Approved :: MIT License
Classifier: Operating System :: OS Independent
Classifier: Programming Language :: Python :: 2.7
Classifier: Programming Language :: Python :: 3.4
Classifier: Programming Language :: Python :: 3.5
Classifier: Programming Language :: Python :: 3.6
Classifier: Programming Language :: Python :: 3.7
